fh_immuta_utils/__init__.py
fh_immuta_utils/authenticate.py
fh_immuta_utils/client.py
fh_immuta_utils/config.py
fh_immuta_utils/data_source.py
fh_immuta_utils/exceptions.py
fh_immuta_utils/log.py
fh_immuta_utils/paginator.py
fh_immuta_utils/policy.py
fh_immuta_utils/tagging.py
fh_immuta_utils/scripts/__init__.py
fh_immuta_utils/scripts/bulk_create_example.py
fh_immuta_utils/scripts/bulk_delete_data_source.py
fh_immuta_utils/scripts/cli.py
fh_immuta_utils/scripts/manage_data_sources.py
fh_immuta_utils/scripts/manage_policies.py
fh_immuta_utils/scripts/tag_existing_data_sources.py
fh_immuta_utils/tests/__init__.py
fh_immuta_utils/tests/test_client.py
fh_immuta_utils/tests/test_data_source.py
fh_immuta_utils/tests/test_policy.py
fh_immuta_utils/tests/test_tagging.py
fh_immuta_utils-0.5.2.dist-info/LICENSE.md
fh_immuta_utils-0.5.2.dist-info/METADATA
fh_immuta_utils-0.5.2.dist-info/WHEEL
fh_immuta_utils-0.5.2.dist-info/entry_points.txt
fh_immuta_utils-0.5.2.dist-info/top_level.txt
fh_immuta_utils-0.5.2.dist-info/RECORD
