Metadata-Version: 2.1
Name: fh-immuta-utils
Version: 0.5.2
Summary: Flatiron Immuta API
Home-page: https://github.com/flatironhealth/fh-immuta-utils
Author-email: data-tooling@flatiron.com
License: UNKNOWN
Platform: UNKNOWN
Classifier: Programming Language :: Python :: 3 :: Only
Classifier: License :: OSI Approved :: BSD License
Classifier: Operating System :: OS Independent
Classifier: Development Status :: 5 - Production/Stable
Requires-Python: >=3.6
Requires-Dist: click
Requires-Dist: hvac
Requires-Dist: pydantic
Requires-Dist: PyYAML
Requires-Dist: requests
Requires-Dist: six
Requires-Dist: toolz
Requires-Dist: tqdm
Requires-Dist: urllib3
